funniestjoke/__init__.py
funniestjoke-0.3.dist-info/METADATA
funniestjoke-0.3.dist-info/WHEEL
funniestjoke-0.3.dist-info/top_level.txt
funniestjoke-0.3.dist-info/RECORD
