Metadata-Version: 2.1
Name: funniestjoke
Version: 0.3
Summary: The funniest joke in the world
Home-page: http://github.com/purushothamkdr453/funniestjoke
Author: purushotham reddy
Author-email: purushothamkdr453@gmail.com
License: MIT
Platform: UNKNOWN
Requires-Dist: Markdown
